{
    "name": {
        "en": "Chongqing",
        "zh-CN": "重庆",
        "zh-HK": "重慶"
    },
    "desc": {
        "en": ""
    },
    "reference": "https://jtj.cq.gov.cn/zwgk_240/zfxxgkml/gggs/tzgg/202302/t20230223_11643527.html#:~:text=%E9%87%8D%E5%BA%86%E8%BD%A8%E9%81%93%E4%BA%A4%E9%80%9A%E7%BA%BF%E7%BD%91,1%E6%9C%88%E7%89%88%EF%BC%89.pdf",
    "updateHistory": [
        {
            "id": 123074394,
            "issueNumber": 41,
            "reason": "Add template of Chongqing",
            "time": 1683810518708
        },
        {
            "id": 123074394,
            "issueNumber": 58,
            "reason": "Remove redundant node in the top left corner.",
            "time": 1684158673359
        },
        {
            "id": 123074394,
            "issueNumber": 409,
            "reason": "将暂未开通的5号线中段与10号线后段取消，更新谢家湾站内换乘与谢家湾、观音桥错误站名",
            "time": 1690893174593
        },
        {
            "id": 123074394,
            "issueNumber": 468,
            "reason": "Added rivers announced lines 5 10 rear passes  line 18 line logos and line colors  changed style",
            "time": 1691550925466
        },
        {
            "id": 123074394,
            "issueNumber": 483,
            "reason": "更新线路颜色",
            "time": 1691590029592
        }
    ]
}