{
    "name": {
        "en": " TIANJIN"
    },
    "desc": {
        "en": ""
    },
    "reference": "https://railmapgen.org/",
    "updateHistory": [
        {
            "id": 135576966,
            "issueNumber": 277,
            "reason": "new",
            "time": 1687403889948
        },
        {
            "id": 138379438,
            "issueNumber": 302,
            "reason": "Make the picture form closer to the official picture",
            "time": 1695461970484
        },
        {
            "id": 138973971,
            "issueNumber": 1373,
            "reason": "Add line 11",
            "time": 1711452291220
        },
        {
            "id": 139970605,
            "issueNumber": 1575,
            "reason": "Update opening status of SHUANGQIAOHE Station and transfer station style.",
            "time": 1720003608179
        },
        {
            "id": 154876632,
            "issueNumber": 1834,
            "reason": "update JINJING Line Line 5 extend to JINHUADONGDAO station",
            "time": 1729056776080
        },
        {
            "id": 154876632,
            "issueNumber": 1926,
            "reason": "Line 2 JIANGUODAO Station renamed as JIANGUODAOYIFENGQU",
            "time": 1732630951969
        },
        {
            "id": 123239445,
            "issueNumber": 2100,
            "reason": "Add newly opened Line 11 West Section and update map layout",
            "time": 1735625232639
        },
        {
            "id": 197052294,
            "issueNumber": 2759,
            "reason": "Add north section of line4",
            "time": 1752218034576
        },
        {
            "id": 220876584,
            "issueNumber": 2771,
            "reason": "New template of ",
            "time": 1752573332354
        }
    ]
}