{
    "name": {
        "en": "Xuzhou",
        "zh-Hans": "徐州",
        "zh-Hant": "徐州"
    },
    "desc": {
        "en": ""
    },
    "reference": "https://www.xzdtjt.com/article/51/xlt/3870.html",
    "updateHistory": [
        {
            "id": 123074394,
            "issueNumber": 319,
            "reason": "9",
            "time": 1688634860783
        },
        {
            "id": 191124802,
            "issueNumber": 1991,
            "reason": "Xuzhou Metro Line 3 Phase 2 Update",
            "time": 1733836024740
        }
    ]
}